pretty_cron/__init__.py
pretty_cron/api.py
pretty_cron-1.1.0.dist-info/LICENSE.txt
pretty_cron-1.1.0.dist-info/METADATA
pretty_cron-1.1.0.dist-info/RECORD
pretty_cron-1.1.0.dist-info/WHEEL
pretty_cron-1.1.0.dist-info/top_level.txt
