Metadata-Version: 2.1
Name: pretty-cron
Version: 1.1.0
Summary: Converts crontab expressions to human-readable descriptions.
Home-page: https://github.com/adamchainz/pretty-cron
Author: Adam Johnson
Author-email: me@adamj.eu
License: MIT
Keywords: c,r,o,n
Platform: UNKNOWN
Classifier: Development Status :: 5 - Production/Stable
Classifier: Intended Audience :: Developers
Classifier: License :: OSI Approved :: MIT License
Classifier: Natural Language :: English
Classifier: Operating System :: OS Independent
Classifier: Programming Language :: Python :: 2
Classifier: Programming Language :: Python :: 2.7
Classifier: Programming Language :: Python :: 3
Classifier: Programming Language :: Python :: 3.4
Classifier: Programming Language :: Python :: 3.5
Classifier: Programming Language :: Python :: 3.6
Requires-Python: >=2.7, !=3.0.*, !=3.1.*, !=3.2.*, !=3.3.*
